<annotation>
	<folder>Dataset</folder>
	<filename>247.jpg</filename>
	<path>C:\Users\Sekyere Amponsah\Desktop\Twist\Dataset\247.jpg</path>
	<source>
		<database>Unknown</database>
	</source>
	<size>
		<width>612</width>
		<height>408</height>
		<depth>3</depth>
	</size>
	<segmented>0</segmented>
	<object>
		<name>with mask</name>
		<pose>Unspecified</pose>
		<truncated>0</truncated>
		<difficult>0</difficult>
		<bndbox>
			<xmin>83</xmin>
			<ymin>99</ymin>
			<xmax>200</xmax>
			<ymax>244</ymax>
		</bndbox>
	</object>
	<object>
		<name>with mask</name>
		<pose>Unspecified</pose>
		<truncated>0</truncated>
		<difficult>0</difficult>
		<bndbox>
			<xmin>312</xmin>
			<ymin>84</ymin>
			<xmax>467</xmax>
			<ymax>261</ymax>
		</bndbox>
	</object>
</annotation>
