<annotation>
	<folder>Dataset</folder>
	<filename>975.jpg</filename>
	<path>C:\Users\Sekyere Amponsah\Desktop\Twist\Dataset\975.jpg</path>
	<source>
		<database>Unknown</database>
	</source>
	<size>
		<width>612</width>
		<height>408</height>
		<depth>3</depth>
	</size>
	<segmented>0</segmented>
	<object>
		<name>without mask</name>
		<pose>Unspecified</pose>
		<truncated>0</truncated>
		<difficult>0</difficult>
		<bndbox>
			<xmin>60</xmin>
			<ymin>218</ymin>
			<xmax>131</xmax>
			<ymax>290</ymax>
		</bndbox>
	</object>
	<object>
		<name>without mask</name>
		<pose>Unspecified</pose>
		<truncated>0</truncated>
		<difficult>0</difficult>
		<bndbox>
			<xmin>427</xmin>
			<ymin>265</ymin>
			<xmax>498</xmax>
			<ymax>337</ymax>
		</bndbox>
	</object>
	<object>
		<name>without mask</name>
		<pose>Unspecified</pose>
		<truncated>0</truncated>
		<difficult>0</difficult>
		<bndbox>
			<xmin>451</xmin>
			<ymin>203</ymin>
			<xmax>522</xmax>
			<ymax>275</ymax>
		</bndbox>
	</object>
</annotation>
